bctool/__init__.py
bctool/bctool.py
bctool-0.0.1.dist-info/METADATA
bctool-0.0.1.dist-info/WHEEL
bctool-0.0.1.dist-info/entry_points.txt
bctool-0.0.1.dist-info/top_level.txt
bctool-0.0.1.dist-info/RECORD
