Metadata-Version: 2.1
Name: bctool
Version: 0.0.1
Summary: beancount tools
Author-email: "qiaohao.peng" <qiaohao.peng@outlook.com>
License: MIT
Requires-Python: >=3.12
Requires-Dist: beancount>=3.0.0
Requires-Dist: click>=8.1.7
